django_naguine-1.0.0.dist-info/DESCRIPTION.rst
django_naguine-1.0.0.dist-info/METADATA
django_naguine-1.0.0.dist-info/RECORD
django_naguine-1.0.0.dist-info/WHEEL
django_naguine-1.0.0.dist-info/metadata.json
django_naguine-1.0.0.dist-info/top_level.txt
naguine/__init__.py
naguine/apps/__init__.py
naguine/apps/models.py
naguine/conf/__init__.py
naguine/core/__init__.py
naguine/core/composedfunction.py
naguine/core/fork.py
