Metadata-Version: 2.0
Name: django-naguine
Version: 1.0.0
Summary: Django Web Framework's sidekick, Sophie "Naguine" Ziegler.
Home-page: https://github.com/colexyz/django-naguine
Author: Cole Carter
Author-email: coleccarter@gmail.com
License: BSD
Platform: UNKNOWN
Classifier: Development Status :: 5 - Production/Stable
Classifier: Environment :: Web Environment
Classifier: Framework :: Django
Classifier: Framework :: Django :: 2.0
Classifier: Framework :: Django :: 2.1
Classifier: Intended Audience :: Developers
Classifier: License :: OSI Approved :: BSD License
Classifier: Programming Language :: Python
Classifier: Programming Language :: Python :: 3.6
Requires-Python: >=3.6
Requires-Dist: Django (>=2.0)
